docling_analysis_framework/__init__.py
docling_analysis_framework/unified_interface.py
docling_analysis_framework/core/__init__.py
docling_analysis_framework/core/analyzer.py
docling_analysis_framework/core/chunking.py
docling_analysis_framework-1.1.0.dist-info/licenses/LICENSE
docling_analysis_framework-1.1.0.dist-info/METADATA
docling_analysis_framework-1.1.0.dist-info/WHEEL
docling_analysis_framework-1.1.0.dist-info/entry_points.txt
docling_analysis_framework-1.1.0.dist-info/top_level.txt
docling_analysis_framework-1.1.0.dist-info/RECORD
