Metadata-Version: 2.4
Name: docling-analysis-framework
Version: 1.1.0
Summary: AI-ready analysis framework for PDF and Office documents using Docling for content extraction
Home-page: https://github.com/rdwj/docling-analysis-framework
Author: Wes Jackson
Author-email: AI Building Blocks <wjackson@redhat.com>
License: MIT
Project-URL: Homepage, https://github.com/rdwj/docling-analysis-framework
Project-URL: Repository, https://github.com/rdwj/docling-analysis-framework
Project-URL: Issues, https://github.com/rdwj/docling-analysis-framework/issues
Project-URL: Documentation, https://github.com/rdwj/docling-analysis-framework/blob/main/README.md
Keywords: docling,pdf,office,ai,ml,document-processing,semantic-search,chunking
Classifier: Development Status :: 5 - Production/Stable
Classifier: Intended Audience :: Developers
Classifier: Topic :: Software Development :: Libraries :: Python Modules
Classifier: Topic :: Text Processing :: General
Classifier: Topic :: Scientific/Engineering :: Artificial Intelligence
Classifier: Topic :: Office/Business :: Office Suites
Classifier: License :: OSI Approved :: MIT License
Classifier: Programming Language :: Python :: 3
Classifier: Programming Language :: Python :: 3.8
Classifier: Programming Language :: Python :: 3.9
Classifier: Programming Language :: Python :: 3.10
Classifier: Programming Language :: Python :: 3.11
Classifier: Programming Language :: Python :: 3.12
Requires-Python: >=3.8
License-File: LICENSE
Requires-Dist: docling>=1.0.0
Provides-Extra: dev
Requires-Dist: pytest>=6.0; extra == "dev"
Requires-Dist: black>=21.0; extra == "dev"
Requires-Dist: flake8>=3.8; extra == "dev"
Requires-Dist: mypy>=0.800; extra == "dev"
Provides-Extra: docs
Requires-Dist: sphinx>=3.0; extra == "docs"
Requires-Dist: sphinx_rtd_theme>=0.5; extra == "docs"
Dynamic: author
Dynamic: home-page
Dynamic: license-file
Dynamic: requires-python
